{
  "mode": "pre",
  "tag": "rc",
  "initialVersions": {
    "nanobundle": "0.0.28"
  },
  "changesets": [
    "big-fishes-dance",
    "chatty-ligers-collect",
    "cold-sloths-chew",
    "cool-chicken-wait",
    "empty-grapes-melt",
    "fresh-knives-greet",
    "great-onions-jump",
    "hot-chairs-speak",
    "lovely-rats-help",
    "lucky-grapes-crash",
    "moody-eagles-collect",
    "quiet-bottles-sit",
    "rude-kangaroos-hide",
    "serious-bugs-accept",
    "seven-houses-report",
    "small-ants-turn",
    "tender-boxes-approve",
    "thin-sloths-draw",
    "tidy-moose-sneeze",
    "tiny-lizards-march",
    "unlucky-beers-think",
    "wicked-camels-buy"
  ]
}
